{"v":1,"episode":130,"episodeDurationSec":11875,"speakers":["Pavel Mayer","Tim Pritlove"],"speakerStats":{"Pavel Mayer":{"overall":{"totalSpeakingTimeSec":5985.124137931034,"segmentCount":73,"longestMonologueSec":521,"shortestSegmentSec":1,"averageSegmentDurationSec":81.98800188946622,"medianSegmentDurationSec":40,"varianceSegmentDurationSec":11066.75009076266,"stdDevSegmentDurationSec":105.1986220953614,"boxplot":{"min":1,"q1":9.5,"median":40,"q3":125.5,"max":479},"speakingShare":0.5053243336722181},"temporal":[{"intervalStartSec":0,"intervalEndSec":600,"totalSpeakingTimeSec":154,"segmentCount":3,"longestMonologueSec":125,"shortestSegmentSec":2,"averageSegmentDurationSec":51.333333333333336,"medianSegmentDurationSec":27,"varianceSegmentDurationSec":2817.555555555555,"stdDevSegmentDurationSec":53.080651423617205,"boxplot":{"min":2,"q1":2,"median":27,"q3":125,"max":125},"speakingShare":0.2664359861591695},{"intervalStartSec":600,"intervalEndSec":1200,"totalSpeakingTimeSec":386,"segmentCount":3,"longestMonologueSec":276,"shortestSegmentSec":47,"averageSegmentDurationSec":128.66666666666666,"medianSegmentDurationSec":63,"varianceSegmentDurationSec":10896.22222222222,"stdDevSegmentDurationSec":104.38497124692913,"boxplot":{"min":47,"q1":47,"median":63,"q3":276,"max":276},"speakingShare":0.5482954545454546},{"intervalStartSec":1200,"intervalEndSec":1800,"totalSpeakingTimeSec":377,"segmentCount":5,"longestMonologueSec":209,"shortestSegmentSec":2,"averageSegmentDurationSec":75.4,"medianSegmentDurationSec":42,"varianceSegmentDurationSec":5460.64,"stdDevSegmentDurationSec":73.89614333644212,"boxplot":{"min":2,"q1":14,"median":42,"q3":153.5,"max":209},"speakingShare":0.647766323024055},{"intervalStartSec":1800,"intervalEndSec":2400,"totalSpeakingTimeSec":68,"segmentCount":3,"longestMonologueSec":45,"shortestSegmentSec":4,"averageSegmentDurationSec":22.666666666666668,"medianSegmentDurationSec":19,"varianceSegmentDurationSec":286.8888888888889,"stdDevSegmentDurationSec":16.937794687883336,"boxplot":{"min":4,"q1":4,"median":19,"q3":45,"max":45},"speakingShare":0.11276948590381426},{"intervalStartSec":2400,"intervalEndSec":3000,"totalSpeakingTimeSec":632,"segmentCount":4,"longestMonologueSec":362,"shortestSegmentSec":59,"averageSegmentDurationSec":158,"medianSegmentDurationSec":105.5,"varianceSegmentDurationSec":15178.5,"stdDevSegmentDurationSec":123.20105519028643,"boxplot":{"min":59,"q1":60.5,"median":105.5,"q3":255.5,"max":362},"speakingShare":0.7435294117647059},{"intervalStartSec":3000,"intervalEndSec":3600,"totalSpeakingTimeSec":207,"segmentCount":3,"longestMonologueSec":192,"shortestSegmentSec":7,"averageSegmentDurationSec":69,"medianSegmentDurationSec":8,"varianceSegmentDurationSec":7564.666666666667,"stdDevSegmentDurationSec":86.9750922199377,"boxplot":{"min":7,"q1":7,"median":8,"q3":192,"max":192},"speakingShare":0.6592356687898089},{"intervalStartSec":3600,"intervalEndSec":4200,"totalSpeakingTimeSec":199,"segmentCount":2,"longestMonologueSec":153,"shortestSegmentSec":46,"averageSegmentDurationSec":99.5,"medianSegmentDurationSec":99.5,"varianceSegmentDurationSec":2862.25,"stdDevSegmentDurationSec":53.5,"boxplot":{"min":46,"q1":46,"median":99.5,"q3":153,"max":153},"speakingShare":0.24238733252131547},{"intervalStartSec":4200,"intervalEndSec":4800,"totalSpeakingTimeSec":304,"segmentCount":3,"longestMonologueSec":156,"shortestSegmentSec":1,"averageSegmentDurationSec":101.33333333333333,"medianSegmentDurationSec":147,"varianceSegmentDurationSec":5046.88888888889,"stdDevSegmentDurationSec":71.04145894397784,"boxplot":{"min":1,"q1":1,"median":147,"q3":156,"max":156},"speakingShare":0.49270664505672607},{"intervalStartSec":4800,"intervalEndSec":5400,"totalSpeakingTimeSec":41,"segmentCount":3,"longestMonologueSec":22,"shortestSegmentSec":2,"averageSegmentDurationSec":13.666666666666666,"medianSegmentDurationSec":17,"varianceSegmentDurationSec":72.22222222222221,"stdDevSegmentDurationSec":8.498365855987974,"boxplot":{"min":2,"q1":2,"median":17,"q3":22,"max":22},"speakingShare":0.13141025641025642},{"intervalStartSec":5400,"intervalEndSec":6000,"totalSpeakingTimeSec":543,"segmentCount":3,"longestMonologueSec":479,"shortestSegmentSec":24,"averageSegmentDurationSec":181,"medianSegmentDurationSec":40,"varianceSegmentDurationSec":44444.666666666664,"stdDevSegmentDurationSec":210.81903772350984,"boxplot":{"min":24,"q1":24,"median":40,"q3":479,"max":479},"speakingShare":0.905},{"intervalStartSec":6000,"intervalEndSec":6600,"totalSpeakingTimeSec":263,"segmentCount":3,"longestMonologueSec":246,"shortestSegmentSec":2,"averageSegmentDurationSec":87.66666666666667,"medianSegmentDurationSec":15,"varianceSegmentDurationSec":12562.888888888885,"stdDevSegmentDurationSec":112.08429367618322,"boxplot":{"min":2,"q1":2,"median":15,"q3":246,"max":246},"speakingShare":0.2622133599202393},{"intervalStartSec":6600,"intervalEndSec":7200,"totalSpeakingTimeSec":56,"segmentCount":2,"longestMonologueSec":44,"shortestSegmentSec":12,"averageSegmentDurationSec":28,"medianSegmentDurationSec":28,"varianceSegmentDurationSec":256,"stdDevSegmentDurationSec":16,"boxplot":{"min":12,"q1":12,"median":28,"q3":44,"max":44},"speakingShare":0.2994652406417112},{"intervalStartSec":7200,"intervalEndSec":7800,"totalSpeakingTimeSec":510,"segmentCount":7,"longestMonologueSec":299,"shortestSegmentSec":4,"averageSegmentDurationSec":72.85714285714286,"medianSegmentDurationSec":11,"varianceSegmentDurationSec":11605.836734693878,"stdDevSegmentDurationSec":107.73038909562091,"boxplot":{"min":4,"q1":5,"median":11,"q3":169,"max":299},"speakingShare":0.8056872037914692},{"intervalStartSec":7800,"intervalEndSec":8400,"totalSpeakingTimeSec":304,"segmentCount":7,"longestMonologueSec":201,"shortestSegmentSec":3,"averageSegmentDurationSec":43.42857142857143,"medianSegmentDurationSec":8,"varianceSegmentDurationSec":4507.102040816326,"stdDevSegmentDurationSec":67.13495394216284,"boxplot":{"min":3,"q1":3,"median":8,"q3":62,"max":201},"speakingShare":0.5126475548060708},{"intervalStartSec":8400,"intervalEndSec":9000,"totalSpeakingTimeSec":351,"segmentCount":6,"longestMonologueSec":202,"shortestSegmentSec":8,"averageSegmentDurationSec":58.5,"medianSegmentDurationSec":26,"varianceSegmentDurationSec":4566.583333333333,"stdDevSegmentDurationSec":67.57649986003517,"boxplot":{"min":8,"q1":16,"median":26,"q3":73,"max":202},"speakingShare":0.6030927835051546},{"intervalStartSec":9000,"intervalEndSec":9600,"totalSpeakingTimeSec":442,"segmentCount":4,"longestMonologueSec":243,"shortestSegmentSec":54,"averageSegmentDurationSec":110.5,"medianSegmentDurationSec":72.5,"varianceSegmentDurationSec":5910.25,"stdDevSegmentDurationSec":76.87815034195347,"boxplot":{"min":54,"q1":62.5,"median":72.5,"q3":158.5,"max":243},"speakingShare":0.5732814526588845},{"intervalStartSec":9600,"intervalEndSec":10200,"totalSpeakingTimeSec":294,"segmentCount":6,"longestMonologueSec":126,"shortestSegmentSec":1,"averageSegmentDurationSec":49,"medianSegmentDurationSec":27,"varianceSegmentDurationSec":2298.6666666666665,"stdDevSegmentDurationSec":47.94441225697387,"boxplot":{"min":1,"q1":11,"median":27,"q3":102,"max":126},"speakingShare":0.5434380776340111},{"intervalStartSec":10200,"intervalEndSec":10800,"totalSpeakingTimeSec":486,"segmentCount":2,"longestMonologueSec":454,"shortestSegmentSec":32,"averageSegmentDurationSec":243,"medianSegmentDurationSec":243,"varianceSegmentDurationSec":44521,"stdDevSegmentDurationSec":211,"boxplot":{"min":32,"q1":32,"median":243,"q3":454,"max":454},"speakingShare":0.5237068965517241},{"intervalStartSec":10800,"intervalEndSec":11400,"totalSpeakingTimeSec":67,"segmentCount":1,"longestMonologueSec":67,"shortestSegmentSec":67,"averageSegmentDurationSec":67,"medianSegmentDurationSec":67,"varianceSegmentDurationSec":0,"stdDevSegmentDurationSec":0,"boxplot":{"min":67,"q1":0,"median":67,"q3":0,"max":67},"speakingShare":0.44370860927152317},{"intervalStartSec":11400,"intervalEndSec":11875,"totalSpeakingTimeSec":301.1241379310345,"segmentCount":3,"longestMonologueSec":218,"shortestSegmentSec":2,"averageSegmentDurationSec":100.37471264367817,"medianSegmentDurationSec":81.12413793103448,"varianceSegmentDurationSec":7961.292313383537,"stdDevSegmentDurationSec":89.22607417892786,"boxplot":{"min":2,"q1":2,"median":81.12413793103448,"q3":218,"max":218},"speakingShare":0.6351166579391401}]},"Tim Pritlove":{"overall":{"totalSpeakingTimeSec":5859,"segmentCount":73,"longestMonologueSec":677,"shortestSegmentSec":1,"averageSegmentDurationSec":80.26027397260275,"medianSegmentDurationSec":49,"varianceSegmentDurationSec":13379.671983486585,"stdDevSegmentDurationSec":115.67053204462485,"boxplot":{"min":1,"q1":5,"median":49,"q3":106,"max":677},"speakingShare":0.4946756663277819},"temporal":[{"intervalStartSec":0,"intervalEndSec":600,"totalSpeakingTimeSec":424,"segmentCount":4,"longestMonologueSec":227,"shortestSegmentSec":3,"averageSegmentDurationSec":106,"medianSegmentDurationSec":97,"varianceSegmentDurationSec":9395,"stdDevSegmentDurationSec":96.92780818733084,"boxplot":{"min":3,"q1":11,"median":97,"q3":201,"max":227},"speakingShare":0.7335640138408305},{"intervalStartSec":600,"intervalEndSec":1200,"totalSpeakingTimeSec":318,"segmentCount":3,"longestMonologueSec":179,"shortestSegmentSec":9,"averageSegmentDurationSec":106,"medianSegmentDurationSec":130,"varianceSegmentDurationSec":5104.666666666667,"stdDevSegmentDurationSec":71.44695001654492,"boxplot":{"min":9,"q1":9,"median":130,"q3":179,"max":179},"speakingShare":0.45170454545454547},{"intervalStartSec":1200,"intervalEndSec":1800,"totalSpeakingTimeSec":205,"segmentCount":4,"longestMonologueSec":74,"shortestSegmentSec":17,"averageSegmentDurationSec":51.25,"medianSegmentDurationSec":57,"varianceSegmentDurationSec":471.1875,"stdDevSegmentDurationSec":21.706853756359994,"boxplot":{"min":17,"q1":33,"median":57,"q3":69.5,"max":74},"speakingShare":0.35223367697594504},{"intervalStartSec":1800,"intervalEndSec":2400,"totalSpeakingTimeSec":535,"segmentCount":4,"longestMonologueSec":261,"shortestSegmentSec":50,"averageSegmentDurationSec":133.75,"medianSegmentDurationSec":112,"varianceSegmentDurationSec":7898.6875,"stdDevSegmentDurationSec":88.87456047711291,"boxplot":{"min":50,"q1":50.5,"median":112,"q3":217,"max":261},"speakingShare":0.8872305140961857},{"intervalStartSec":2400,"intervalEndSec":3000,"totalSpeakingTimeSec":218,"segmentCount":3,"longestMonologueSec":130,"shortestSegmentSec":1,"averageSegmentDurationSec":72.66666666666667,"medianSegmentDurationSec":87,"varianceSegmentDurationSec":2876.2222222222226,"stdDevSegmentDurationSec":53.63042254375983,"boxplot":{"min":1,"q1":1,"median":87,"q3":130,"max":130},"speakingShare":0.2564705882352941},{"intervalStartSec":3000,"intervalEndSec":3600,"totalSpeakingTimeSec":107,"segmentCount":3,"longestMonologueSec":97,"shortestSegmentSec":4,"averageSegmentDurationSec":35.666666666666664,"medianSegmentDurationSec":6,"varianceSegmentDurationSec":1881.5555555555557,"stdDevSegmentDurationSec":43.37690117511342,"boxplot":{"min":4,"q1":4,"median":6,"q3":97,"max":97},"speakingShare":0.34076433121019106},{"intervalStartSec":3600,"intervalEndSec":4200,"totalSpeakingTimeSec":622,"segmentCount":3,"longestMonologueSec":531,"shortestSegmentSec":20,"averageSegmentDurationSec":207.33333333333334,"medianSegmentDurationSec":71,"varianceSegmentDurationSec":52813.55555555554,"stdDevSegmentDurationSec":229.81200046027956,"boxplot":{"min":20,"q1":20,"median":71,"q3":531,"max":531},"speakingShare":0.7576126674786845},{"intervalStartSec":4200,"intervalEndSec":4800,"totalSpeakingTimeSec":313,"segmentCount":3,"longestMonologueSec":305,"shortestSegmentSec":1,"averageSegmentDurationSec":104.33333333333333,"medianSegmentDurationSec":7,"varianceSegmentDurationSec":20139.55555555556,"stdDevSegmentDurationSec":141.91390191082604,"boxplot":{"min":1,"q1":1,"median":7,"q3":305,"max":305},"speakingShare":0.5072933549432739},{"intervalStartSec":4800,"intervalEndSec":5400,"totalSpeakingTimeSec":271,"segmentCount":3,"longestMonologueSec":163,"shortestSegmentSec":1,"averageSegmentDurationSec":90.33333333333333,"medianSegmentDurationSec":107,"varianceSegmentDurationSec":4512.888888888889,"stdDevSegmentDurationSec":67.17803873952326,"boxplot":{"min":1,"q1":1,"median":107,"q3":163,"max":163},"speakingShare":0.8685897435897436},{"intervalStartSec":5400,"intervalEndSec":6000,"totalSpeakingTimeSec":57,"segmentCount":3,"longestMonologueSec":50,"shortestSegmentSec":2,"averageSegmentDurationSec":19,"medianSegmentDurationSec":5,"varianceSegmentDurationSec":482,"stdDevSegmentDurationSec":21.95449840010015,"boxplot":{"min":2,"q1":2,"median":5,"q3":50,"max":50},"speakingShare":0.095},{"intervalStartSec":6000,"intervalEndSec":6600,"totalSpeakingTimeSec":740,"segmentCount":3,"longestMonologueSec":677,"shortestSegmentSec":5,"averageSegmentDurationSec":246.66666666666666,"medianSegmentDurationSec":58,"varianceSegmentDurationSec":93061.55555555556,"stdDevSegmentDurationSec":305.0599212540965,"boxplot":{"min":5,"q1":5,"median":58,"q3":677,"max":677},"speakingShare":0.7377866400797607},{"intervalStartSec":6600,"intervalEndSec":7200,"totalSpeakingTimeSec":131,"segmentCount":2,"longestMonologueSec":105,"shortestSegmentSec":26,"averageSegmentDurationSec":65.5,"medianSegmentDurationSec":65.5,"varianceSegmentDurationSec":1560.25,"stdDevSegmentDurationSec":39.5,"boxplot":{"min":26,"q1":26,"median":65.5,"q3":105,"max":105},"speakingShare":0.7005347593582888},{"intervalStartSec":7200,"intervalEndSec":7800,"totalSpeakingTimeSec":123,"segmentCount":7,"longestMonologueSec":67,"shortestSegmentSec":1,"averageSegmentDurationSec":17.571428571428573,"medianSegmentDurationSec":7,"varianceSegmentDurationSec":479.3877551020409,"stdDevSegmentDurationSec":21.89492532761966,"boxplot":{"min":1,"q1":2,"median":7,"q3":23,"max":67},"speakingShare":0.1943127962085308},{"intervalStartSec":7800,"intervalEndSec":8400,"totalSpeakingTimeSec":289,"segmentCount":6,"longestMonologueSec":93,"shortestSegmentSec":1,"averageSegmentDurationSec":48.166666666666664,"medianSegmentDurationSec":52.5,"varianceSegmentDurationSec":1175.8055555555557,"stdDevSegmentDurationSec":34.29002122419226,"boxplot":{"min":1,"q1":10,"median":52.5,"q3":80,"max":93},"speakingShare":0.4873524451939292},{"intervalStartSec":8400,"intervalEndSec":9000,"totalSpeakingTimeSec":231,"segmentCount":6,"longestMonologueSec":188,"shortestSegmentSec":3,"averageSegmentDurationSec":38.5,"medianSegmentDurationSec":7,"varianceSegmentDurationSec":4518.916666666667,"stdDevSegmentDurationSec":67.2228879673186,"boxplot":{"min":3,"q1":3,"median":7,"q3":23,"max":188},"speakingShare":0.39690721649484534},{"intervalStartSec":9000,"intervalEndSec":9600,"totalSpeakingTimeSec":329,"segmentCount":4,"longestMonologueSec":169,"shortestSegmentSec":4,"averageSegmentDurationSec":82.25,"medianSegmentDurationSec":78,"varianceSegmentDurationSec":6085.6875,"stdDevSegmentDurationSec":78.01081655770564,"boxplot":{"min":4,"q1":4.5,"median":78,"q3":160,"max":169},"speakingShare":0.4267185473411154},{"intervalStartSec":9600,"intervalEndSec":10200,"totalSpeakingTimeSec":247,"segmentCount":6,"longestMonologueSec":143,"shortestSegmentSec":1,"averageSegmentDurationSec":41.166666666666664,"medianSegmentDurationSec":11,"varianceSegmentDurationSec":2723.8055555555557,"stdDevSegmentDurationSec":52.190090587730886,"boxplot":{"min":1,"q1":5,"median":11,"q3":76,"max":143},"speakingShare":0.4565619223659889},{"intervalStartSec":10200,"intervalEndSec":10800,"totalSpeakingTimeSec":442,"segmentCount":2,"longestMonologueSec":304,"shortestSegmentSec":138,"averageSegmentDurationSec":221,"medianSegmentDurationSec":221,"varianceSegmentDurationSec":6889,"stdDevSegmentDurationSec":83,"boxplot":{"min":138,"q1":138,"median":221,"q3":304,"max":304},"speakingShare":0.47629310344827586},{"intervalStartSec":10800,"intervalEndSec":11400,"totalSpeakingTimeSec":84,"segmentCount":1,"longestMonologueSec":84,"shortestSegmentSec":84,"averageSegmentDurationSec":84,"medianSegmentDurationSec":84,"varianceSegmentDurationSec":0,"stdDevSegmentDurationSec":0,"boxplot":{"min":84,"q1":0,"median":84,"q3":0,"max":84},"speakingShare":0.5562913907284768},{"intervalStartSec":11400,"intervalEndSec":11875,"totalSpeakingTimeSec":173,"segmentCount":3,"longestMonologueSec":94,"shortestSegmentSec":22,"averageSegmentDurationSec":57.666666666666664,"medianSegmentDurationSec":57,"varianceSegmentDurationSec":864.2222222222222,"stdDevSegmentDurationSec":29.39765674713245,"boxplot":{"min":22,"q1":22,"median":57,"q3":94,"max":94},"speakingShare":0.3648833420608599}]}}}