{
  "episodeNumber": 135,
  "title": "CRE135 Mut zur Freiheit",
  "extractedAt": "2026-01-02T23:20:17.633Z",
  "dataSource": "description",
  "topics": [
    {
      "topic": "Zusammenhang von Angst und Freiheit",
      "subject": {
        "coarse": "Gesellschaft",
        "fine": "Freiheit"
      },
      "summary": "",
      "summaryMeta": {
        "transcriptFound": false,
        "transcriptFile": "135-ts.json"
      }
    },
    {
      "topic": "Bürgerliche Freiheiten",
      "subject": {
        "coarse": "Gesellschaft",
        "fine": "Rechte"
      },
      "summary": "",
      "summaryMeta": {
        "transcriptFound": false,
        "transcriptFile": "135-ts.json"
      }
    },
    {
      "topic": "Migration und Flucht",
      "subject": {
        "coarse": "Gesellschaft",
        "fine": "Migration"
      },
      "summary": "",
      "summaryMeta": {
        "transcriptFound": false,
        "transcriptFile": "135-ts.json"
      }
    },
    {
      "topic": "Freiheit des Flüchtlings",
      "subject": {
        "coarse": "Gesellschaft",
        "fine": "Flüchtlinge"
      },
      "summary": "",
      "summaryMeta": {
        "transcriptFound": false,
        "transcriptFile": "135-ts.json"
      }
    },
    {
      "topic": "Islamistenversteher",
      "subject": {
        "coarse": "Gesellschaft",
        "fine": "Religion"
      },
      "summary": "",
      "summaryMeta": {
        "transcriptFound": false,
        "transcriptFile": "135-ts.json"
      }
    },
    {
      "topic": "Selbstverständnis des Staates",
      "subject": {
        "coarse": "Politik",
        "fine": "Staatsverständnis"
      },
      "summary": "",
      "summaryMeta": {
        "transcriptFound": false,
        "transcriptFile": "135-ts.json"
      }
    },
    {
      "topic": "Antisoziales Verhalten",
      "subject": {
        "coarse": "Gesellschaft",
        "fine": "Verhalten"
      },
      "summary": "",
      "summaryMeta": {
        "transcriptFound": false,
        "transcriptFile": "135-ts.json"
      }
    },
    {
      "topic": "Unsichtbarer Feind",
      "subject": {
        "coarse": "Gesellschaft",
        "fine": "Angst"
      },
      "summary": "",
      "summaryMeta": {
        "transcriptFound": false,
        "transcriptFile": "135-ts.json"
      }
    },
    {
      "topic": "Skandalbesessenheit",
      "subject": {
        "coarse": "Gesellschaft",
        "fine": "Medien"
      },
      "summary": "",
      "summaryMeta": {
        "transcriptFound": false,
        "transcriptFile": "135-ts.json"
      }
    },
    {
      "topic": "Sicherheit und Freiheit",
      "subject": {
        "coarse": "Gesellschaft",
        "fine": "Sicherheit"
      },
      "summary": "",
      "summaryMeta": {
        "transcriptFound": false,
        "transcriptFile": "135-ts.json"
      }
    },
    {
      "topic": "Infantilisierung der Gesellschaft",
      "subject": {
        "coarse": "Gesellschaft",
        "fine": "Kultur"
      },
      "summary": "",
      "summaryMeta": {
        "transcriptFound": false,
        "transcriptFile": "135-ts.json"
      }
    },
    {
      "topic": "Natürliche und artifizielle Ängste",
      "subject": {
        "coarse": "Psychologie",
        "fine": "Ängste"
      },
      "summary": "",
      "summaryMeta": {
        "transcriptFound": false,
        "transcriptFile": "135-ts.json"
      }
    },
    {
      "topic": "Leben ohne Fernsehen und 9/11",
      "subject": {
        "coarse": "Gesellschaft",
        "fine": "Kultur"
      },
      "summary": "",
      "summaryMeta": {
        "transcriptFound": false,
        "transcriptFile": "135-ts.json"
      }
    },
    {
      "topic": "Hessischer Dschihad",
      "subject": {
        "coarse": "Politik",
        "fine": "Terrorismus"
      },
      "summary": "",
      "summaryMeta": {
        "transcriptFound": false,
        "transcriptFile": "135-ts.json"
      }
    },
    {
      "topic": "Terroristische Bedrohung in Deutschland",
      "subject": {
        "coarse": "Politik",
        "fine": "Sicherheit"
      },
      "summary": "",
      "summaryMeta": {
        "transcriptFound": false,
        "transcriptFile": "135-ts.json"
      }
    },
    {
      "topic": "Gesellschaftlicher Widerstand",
      "subject": {
        "coarse": "Gesellschaft",
        "fine": "Widerstand"
      },
      "summary": "",
      "summaryMeta": {
        "transcriptFound": false,
        "transcriptFile": "135-ts.json"
      }
    }
  ],
  "extendedAt": "2026-01-03T00:00:28.803Z",
  "transcriptFound": false,
  "transcriptFile": "135-ts.json"
}
