{
  "title": "LNP151 Lesezirkel im Keller",
  "number": 151,
  "date": "2015-09-02",
  "url": "https://logbuch-netzpolitik.de/lnp151-lesezirkel-im-keller",
  "duration": [
    1,
    30,
    0
  ],
  "description": "Landesverrat — XKeyScore und NSA, BFV BND — Ashley Madison — Dieter Gorny — Kurt Graulich und die VDS — Posteo und die VDS — The Return of the Heveling",
  "speakers": [
    "Linus Neumann",
    "Tim Pritlove"
  ],
  "chapters": [
    "Intro",
    "Prolog",
    "Landesverrat Update",
    "XKeyScore-Vertrag von NSA, BFV, BND",
    "Ashley Madison Hack",
    "Dieter Gorny unhaltbar",
    "Kurt Graulich gegen VDS",
    "Posteo gegen VDS",
    "Heveling löst Bosbach an Spitze von Innenausschuss ab",
    "Epilog"
  ]
}