{
  "episodeNumber": 183,
  "title": "LNP183 Blinde Kuh mit Baseballschläger",
  "extractedAt": "2026-01-02T10:58:56.867Z",
  "dataSource": "detailed-chapters",
  "topics": [
    {
      "topic": "Störerhaftung wurde vielleicht abgeschafft",
      "subject": {
        "coarse": "Law / Liability",
        "fine": "Störerhaftung"
      },
      "durationSec": 886,
      "positionSec": 102
    },
    {
      "topic": "Sampling erlaubt",
      "subject": {
        "coarse": "Law / Copyright",
        "fine": "Sampling"
      },
      "durationSec": 786,
      "positionSec": 989
    },
    {
      "topic": "Android Location History",
      "subject": {
        "coarse": "Technology / Location Services",
        "fine": "Android"
      },
      "durationSec": 1024,
      "positionSec": 1775
    },
    {
      "topic": "Google gewinnt Urheberrechtsstreit gegen Oracle",
      "subject": {
        "coarse": "Law / Copyright",
        "fine": "Urheberrechtsstreit"
      },
      "durationSec": 326,
      "positionSec": 2799
    },
    {
      "topic": "KI lernt Stereotype",
      "subject": {
        "coarse": "AI / Stereotypes",
        "fine": "KI"
      },
      "durationSec": 415,
      "positionSec": 3126
    },
    {
      "topic": "Cyber Cyber Cigarette",
      "subject": {
        "coarse": "Technology / Cybersecurity",
        "fine": "Cyber Cigarette"
      },
      "durationSec": 1057,
      "positionSec": 3541
    },
    {
      "topic": "Fast WLAN in Berlin",
      "subject": {
        "coarse": "Technology / Internet",
        "fine": "WLAN"
      },
      "durationSec": 1098,
      "positionSec": 4599
    },
    {
      "topic": "Netzneutralitätsdemo in Wien",
      "subject": {
        "coarse": "Activism / Net Neutrality",
        "fine": "Demo"
      },
      "durationSec": 97,
      "positionSec": 5697
    }
  ]
}