{
  "episodeNumber": 251,
  "title": "LNP251 Ferteidigung der diskordischen Grundordnung",
  "normalizedAt": "2026-01-02T15:55:30.561Z",
  "taxonomyVersion": "2026-01-02T15:32:56.684Z",
  "topics": [
    {
      "topicId": "datenschutz",
      "relevance": 10,
      "originalTopics": [
        "Facebook schließt 1,5 Milliarden Nutzer von EU-Datenschutz aus",
        "DSGVO in Österreich ohne Zähne",
        "VDS bleibt europarechtswidrig"
      ],
      "topicName": "Datenschutz"
    },
    {
      "topicId": "ueberwachung",
      "relevance": 9,
      "originalTopics": [
        "Sicherheitspaket Österreich mit Zähnen",
        "Big Brother Awards 2018"
      ],
      "topicName": "Überwachung"
    },
    {
      "topicId": "digitales-gesundheitswesen",
      "relevance": 8,
      "originalTopics": [
        "Feedback: Digitales Gesundheitssystem"
      ],
      "topicName": "Digitales Gesundheitswesen"
    },
    {
      "topicId": "netzpolitik",
      "relevance": 7,
      "originalTopics": [
        "Wenigstens Adblocker bleiben legal",
        "Brexit könnte UK-Unternehmen die Domain kosten"
      ],
      "topicName": "Netzpolitik"
    },
    {
      "topicId": "feedback",
      "relevance": 5,
      "originalTopics": [
        "Feedback: Bundesregierung wirbt auf Facebook"
      ],
      "topicName": "Feedback"
    },
    {
      "topicId": "gesellschaft",
      "relevance": 4,
      "originalTopics": [
        "Rainer Wendt, du bist kein echter Polizist"
      ],
      "topicName": "Gesellschaft"
    }
  ]
}