{
  "episodeNumber": 273,
  "title": "LNP273 Die Verfassungskatze",
  "extractedAt": "2026-01-02T11:11:57.030Z",
  "dataSource": "detailed-chapters",
  "topics": [
    {
      "topic": "Privacy Week",
      "subject": {
        "coarse": "Privacy",
        "fine": "Privacy Week"
      },
      "durationSec": 389,
      "positionSec": 326
    },
    {
      "topic": "Arbeitsmarktservice Österreich (AMS) teilt Arbeitslose mit Algorithmus ein",
      "subject": {
        "coarse": "Employment",
        "fine": "Algorithmic Job Allocation"
      },
      "durationSec": 837,
      "positionSec": 716
    },
    {
      "topic": "AFD-Denunziationsstelle gegen Lehrerinnen",
      "subject": {
        "coarse": "Politics",
        "fine": "Denunciation Practices"
      },
      "durationSec": 752,
      "positionSec": 1554
    },
    {
      "topic": "Mozfest 2018",
      "subject": {
        "coarse": "Events",
        "fine": "Mozfest 2018"
      },
      "durationSec": 74,
      "positionSec": 2306
    },
    {
      "topic": "Tim Cook auf ICDPPC",
      "subject": {
        "coarse": "Technology",
        "fine": "Tim Cook"
      },
      "durationSec": 839,
      "positionSec": 2381
    },
    {
      "topic": "ePrivacy: Österreich verzögert die Verhandlungen weiter",
      "subject": {
        "coarse": "Legislation",
        "fine": "ePrivacy Negotiations"
      },
      "durationSec": 581,
      "positionSec": 3221
    },
    {
      "topic": "Facebook-Leck",
      "subject": {
        "coarse": "Social Media",
        "fine": "Facebook Data Breach"
      },
      "durationSec": 822,
      "positionSec": 3802
    }
  ]
}