{
  "chapters": [
    {
      "number": 1,
      "title": "Intro",
      "durationSec": 31,
      "positionSec": 0
    },
    {
      "number": 2,
      "title": "Prolog",
      "durationSec": 137,
      "positionSec": 31
    },
    {
      "number": 3,
      "title": "Feedback: Verbreitung von Luca",
      "durationSec": 94,
      "positionSec": 168
    },
    {
      "number": 4,
      "title": "Feedback: GPL vs. BSD",
      "durationSec": 352,
      "positionSec": 262
    },
    {
      "number": 5,
      "title": "Feedback: Viren vs. Bakterien",
      "durationSec": 291,
      "positionSec": 614
    },
    {
      "number": 6,
      "title": "Feedback: Luca-QR-Codes",
      "durationSec": 38,
      "positionSec": 906
    },
    {
      "number": 7,
      "title": "Nachtrag zur Luca-App",
      "durationSec": 1820,
      "positionSec": 944
    },
    {
      "number": 8,
      "title": "Social Bots",
      "durationSec": 150,
      "positionSec": 2765
    },
    {
      "number": 9,
      "title": "Bestandsdatenauskunft",
      "durationSec": 64,
      "positionSec": 2916
    },
    {
      "number": 10,
      "title": "Schufa CheckNow",
      "durationSec": 90,
      "positionSec": 2980
    },
    {
      "number": 11,
      "title": "Bürger.ID",
      "durationSec": 413,
      "positionSec": 3071
    },
    {
      "number": 12,
      "title": "Android ID",
      "durationSec": 157,
      "positionSec": 3484
    },
    {
      "number": 13,
      "title": "Jobs",
      "durationSec": 139,
      "positionSec": 3641
    },
    {
      "number": 14,
      "title": "Epilog",
      "durationSec": 320,
      "positionSec": 3781
    }
  ]
}